{"detail_activities": [{"activityId": 16465637841, "activityName": "\u677f\u6a4b\u5340 \u8dd1\u6b65", "startTimeLocal": "2024-07-18 04:36:16", "startTimeGMT": "2024-07-17 20:36:16", "activityType": {"typeId": 1, "typeKey": "running", "parentTypeId": 17, "isHidden": false, "restricted": false, "trimmable": true}, "eventType": {"typeId": 9, "typeKey": "uncategorized", "sortOrder": 10}, "distance": 12734.1904296875, "duration": 4881.541015625, "elapsedDuration": 4881.541015625, "movingDuration": 4852.311950683594, "elevationGain": 11.0, "elevationLoss": 13.0, "averageSpeed": 2.6089999675750732, "maxSpeed": 4.479000091552734, "startLatitude": 24.999027969315648, "startLongitude": 121.44743830896914, "hasPolyline": true, "hasImages": false, "ownerId": 2819326, "ownerDisplayName": "czja1760", "ownerFullName": "\u9673\u5efa\u83ef", "ownerProfileImageUrlSmall": "https://connect.garmin.com/images/avatars/avatar_b77d7091-81ff-4eb2-84de-112788c0d9b6_s.png", "ownerProfileImageUrlMedium": "https://connect.garmin.com/images/avatars/avatar_b77d7091-81ff-4eb2-84de-112788c0d9b6_m.png", "ownerProfileImageUrlLarge": "https://connect.garmin.com/images/avatars/avatar_b77d7091-81ff-4eb2-84de-112788c0d9b6.png", "calories": 923.0, "bmrCalories": 108.0, "averageHR": 156.0, "maxHR": 174.0, "averageRunningCadenceInStepsPerMinute": 181.828125, "maxRunningCadenceInStepsPerMinute": 202.0, "steps": 14764, "userRoles": ["SCOPE_GOLF_API_READ", "SCOPE_ATP_READ", "SCOPE_DIVE_API_WRITE", "SCOPE_COMMUNITY_COURSE_ADMIN_READ", "SCOPE_DIVE_API_READ", "SCOPE_DI_OAUTH_2_CLIENT_READ", "SCOPE_CONNECT_WRITE", "SCOPE_COMMUNITY_COURSE_WRITE", "SCOPE_MESSAGE_GENERATION_READ", "SCOPE_DI_OAUTH_2_CLIENT_REVOCATION_ADMIN", "SCOPE_CONNECT_WEB_TEMPLATE_RENDER", "SCOPE_OMT_SUBSCRIPTION_ADMIN_READ", "SCOPE_CONNECT_NON_SOCIAL_SHARED_READ", "SCOPE_CONNECT_READ", "SCOPE_DI_OAUTH_2_TOKEN_ADMIN", "ROLE_CONNECTUSER", "ROLE_FITNESS_USER", "ROLE_WELLNESS_USER", "ROLE_OUTDOOR_USER", "ROLE_CONNECT_2_USER"], "privacy": {"typeId": 3, "typeKey": "subscribers"}, "userPro": false, "hasVideo": false, "timeZoneId": 135, "beginTimestamp": 1721248576000, "sportTypeId": 1, "avgPower": 239.0, "maxPower": 427.0, "aerobicTrainingEffect": 4.199999809265137, "anaerobicTrainingEffect": 0.10000000149011612, "normPower": 244.0, "avgVerticalOscillation": 7.390000152587891, "avgGroundContactTime": 254.6999969482422, "avgStrideLength": 85.37999877929688, "vO2MaxValue": 52.0, "avgVerticalRatio": 8.720000267028809, "deviceId": 3459189856, "minTemperature": 30.0, "maxTemperature": 32.0, "minElevation": 3.4000000953674316, "maxElevation": 9.399999618530273, "maxDoubleCadence": 202.0, "summarizedDiveInfo": {"summarizedDiveGases": []}, "maxVerticalSpeed": 0.40000009536743164, "manufacturer": "GARMIN", "locationName": "\u677f\u6a4b\u5340", "lapCount": 13, "endLatitude": 25.004365732893348, "endLongitude": 121.4405757933855, "waterEstimated": 1355.0, "minRespirationRate": 14.029999732971191, "maxRespirationRate": 43.34000015258789, "avgRespirationRate": 29.690000534057617, "trainingEffectLabel": "VO2MAX", "activityTrainingLoad": 199.17237854003906, "minActivityLapDuration": 303.197998046875, "aerobicTrainingEffectMessage": "HIGHLY_IMPROVING_VO2_MAX_16", "anaerobicTrainingEffectMessage": "NO_ANAEROBIC_BENEFIT_0", "splitSummaries": [{"noOfSplits": 1, "totalAscent": 11.0, "duration": 4881.541015625, "splitType": "INTERVAL_ACTIVE", "numClimbSends": 0, "maxElevationGain": 11.0, "averageElevationGain": 11.0, "maxDistance": 12734, "distance": 12734.1904296875, "averageSpeed": 2.6089999675750732, "maxSpeed": 4.479000091552734, "numFalls": 0, "elevationLoss": 13.0}, {"noOfSplits": 2, "totalAscent": 0.0, "duration": 3.003000020980835, "splitType": "RWD_WALK", "numClimbSends": 0, "maxElevationGain": 0.0, "averageElevationGain": 0.0, "maxDistance": 5, "distance": 7.329999923706055, "averageSpeed": 2.440999984741211, "maxSpeed": 2.7990000247955322, "numFalls": 0, "elevationLoss": 0.0}, {"noOfSplits": 1, "totalAscent": 0.0, "duration": 24.0, "splitType": "RWD_STAND", "numClimbSends": 0, "maxElevationGain": 0.0, "averageElevationGain": 0.0, "maxDistance": 3, "distance": 3.930000066757202, "averageSpeed": 0.164000004529953, "maxSpeed": 0.0, "numFalls": 0, "elevationLoss": 0.0}, {"noOfSplits": 2, "totalAscent": 11.0, "duration": 4855.36181640625, "splitType": "RWD_RUN", "numClimbSends": 0, "maxElevationGain": 10.0, "averageElevationGain": 6.0, "maxDistance": 11994, "distance": 12722.9296875, "averageSpeed": 2.619999885559082, "maxSpeed": 4.479000091552734, "numFalls": 0, "elevationLoss": 13.0}], "hasSplits": true, "moderateIntensityMinutes": 35, "vigorousIntensityMinutes": 27, "avgGradeAdjustedSpeed": 2.6019999980926514, "differenceBodyBattery": -19, "hasHeatMap": false, "hrTimeInZone_1": 75.001, "hrTimeInZone_2": 814.441, "hrTimeInZone_3": 2200.632, "hrTimeInZone_4": 1764.253, "hrTimeInZone_5": 0.0, "powerTimeInZone_1": 2692.894, "powerTimeInZone_2": 1066.641, "powerTimeInZone_3": 67.012, "powerTimeInZone_4": 3.0, "powerTimeInZone_5": 4.0, "endTimeGMT": "2024-07-17 21:57:37", "qualifyingDive": false, "pr": false, "manualActivity": false, "purposeful": false, "autoCalcCalories": false, "elevationCorrected": false, "atpActivity": false, "favorite": false, "decoDive": false, "parent": false, "splits": {"activityId": 16465637841, "lapDTOs": [{"startTimeGMT": "2024-07-17T20:36:16.0", "startLatitude": 24.999027969315648, "startLongitude": 121.44743830896914, "distance": 1000.0, "duration": 416.573, "movingDuration": 390.0, "elapsedDuration": 416.573, "elevationGain": 1.0, "elevationLoss": 0.0, "maxElevation": 9.4, "minElevation": 7.6, "averageSpeed": 2.4010000228881836, "averageMovingSpeed": 2.5641025641025643, "maxSpeed": 2.818000078201294, "calories": 75.0, "bmrCalories": 9.0, "averageHR": 137.0, "maxHR": 147.0, "averageRunCadence": 165.828125, "maxRunCadence": 190.0, "averageTemperature": 31.0, "maxTemperature": 31.0, "minTemperature": 30.0, "averagePower": 220.0, "maxPower": 262.0, "minPower": 0.0, "normalizedPower": 234.0, "totalWork": 21.956935766416393, "groundContactTime": 256.20001220703125, "strideLength": 86.32000122070313, "verticalOscillation": 7.530000305175782, "verticalRatio": 8.729999542236328, "endLatitude": 25.0001304410398, "endLongitude": 121.44016440957785, "maxVerticalSpeed": 0.20000076293945312, "maxRespirationRate": 43.08000183105469, "avgRespirationRate": 36.34000015258789, "directWorkoutComplianceScore": 100, "avgGradeAdjustedSpeed": 2.436000108718872, "lapIndex": 1, "lengthDTOs": [], "connectIQMeasurement": [], "intensityType": "INTERVAL", "messageIndex": 0}, {"startTimeGMT": "2024-07-17T20:43:13.0", "startLatitude": 25.000154078006744, "startLongitude": 121.4401600509882, "distance": 1000.0, "duration": 377.533, "movingDuration": 377.533, "elapsedDuration": 377.533, "elevationGain": 0.0, "elevationLoss": 1.0, "maxElevation": 8.6, "minElevation": 7.6, "averageSpeed": 2.6489999294281006, "averageMovingSpeed": 2.6487751476214414, "maxSpeed": 3.069999933242798, "calories": 73.0, "bmrCalories": 8.0, "averageHR": 144.0, "maxHR": 150.0, "averageRunCadence": 183.5, "maxRunCadence": 190.0, "averageTemperature": 30.0, "maxTemperature": 31.0, "minTemperature": 30.0, "averagePower": 239.0, "maxPower": 296.0, "minPower": 223.0, "normalizedPower": 240.0, "totalWork": 21.479611075842122, "groundContactTime": 253.6999969482422, "strideLength": 86.15, "verticalOscillation": 7.419999694824219, "verticalRatio": 8.609999656677246, "endLatitude": 25.009093126282096, "endLongitude": 121.44107560627162, "maxVerticalSpeed": 0.20000076293945312, "maxRespirationRate": 43.34000015258789, "avgRespirationRate": 37.630001068115234, "directWorkoutComplianceScore": 100, "avgGradeAdjustedSpeed": 2.6440000534057617, "lapIndex": 2, "lengthDTOs": [], "connectIQMeasurement": [], "intensityType": "INTERVAL", "messageIndex": 1}, {"startTimeGMT": "2024-07-17T20:49:31.0", "startLatitude": 25.009117014706135, "startLongitude": 121.4410823956132, "distance": 1000.0, "duration": 381.572, "movingDuration": 381.572, "elapsedDuration": 381.572, "elevationGain": 0.0, "elevationLoss": 2.0, "maxElevation": 7.8, "minElevation": 5.0, "averageSpeed": 2.621000051498413, "averageMovingSpeed": 2.6207374327090394, "maxSpeed": 2.687000036239624, "calories": 73.0, "bmrCalories": 8.0, "averageHR": 148.0, "maxHR": 152.0, "averageRunCadence": 182.890625, "maxRunCadence": 191.0, "averageTemperature": 30.0, "maxTemperature": 31.0, "minTemperature": 30.0, "averagePower": 234.0, "maxPower": 244.0, "minPower": 221.0, "normalizedPower": 234.0, "totalWork": 21.240948730554987, "groundContactTime": 255.39999389648438, "strideLength": 85.02000122070314, "verticalOscillation": 7.409999847412109, "verticalRatio": 8.710000038146973, "endLatitude": 25.017614420503378, "endLongitude": 121.44424304366112, "maxVerticalSpeed": 0.20000028610229495, "maxRespirationRate": 37.790000915527344, "avgRespirationRate": 34.279998779296875, "directWorkoutComplianceScore": 100, "avgGradeAdjustedSpeed": 2.5889999866485596, "lapIndex": 3, "lengthDTOs": [], "connectIQMeasurement": [], "intensityType": "INTERVAL", "messageIndex": 2}, {"startTimeGMT": "2024-07-17T20:55:53.0", "startLatitude": 25.017635291442275, "startLongitude": 121.44425268284976, "distance": 1000.0, "duration": 344.147, "movingDuration": 344.0, "elapsedDuration": 344.147, "elevationGain": 3.0, "elevationLoss": 0.0, "maxElevation": 8.4, "minElevation": 5.0, "averageSpeed": 2.905999898910522, "averageMovingSpeed": 2.9069767441860463, "maxSpeed": 3.1070001125335693, "calories": 72.0, "bmrCalories": 8.0, "averageHR": 159.0, "maxHR": 165.0, "averageRunCadence": 183.03125, "maxRunCadence": 190.0, "averageTemperature": 31.0, "maxTemperature": 31.0, "minTemperature": 30.0, "averagePower": 266.0, "maxPower": 320.0, "minPower": 227.0, "normalizedPower": 265.0, "totalWork": 21.718273421129258, "groundContactTime": 248.5, "strideLength": 94.37999877929688, "verticalOscillation": 7.790000152587891, "verticalRatio": 8.25, "endLatitude": 25.024569975212216, "endLongitude": 121.45012672059238, "maxVerticalSpeed": 0.39999961853027344, "maxRespirationRate": 35.380001068115234, "avgRespirationRate": 28.3799991607666, "directWorkoutComplianceScore": 100, "avgGradeAdjustedSpeed": 2.905999898910522, "lapIndex": 4, "lengthDTOs": [], "connectIQMeasurement": [], "intensityType": "INTERVAL", "messageIndex": 3}, {"startTimeGMT": "2024-07-17T21:01:37.0", "startLatitude": 25.024589505046606, "startLongitude": 121.45014625042677, "distance": 1000.0, "duration": 342.316, "movingDuration": 342.0, "elapsedDuration": 342.316, "elevationGain": 0.0, "elevationLoss": 2.0, "maxElevation": 7.4, "minElevation": 5.8, "averageSpeed": 2.921000003814697, "averageMovingSpeed": 2.9239766081871346, "maxSpeed": 3.069999933242798, "calories": 72.0, "bmrCalories": 8.0, "averageHR": 162.0, "maxHR": 165.0, "averageRunCadence": 183.125, "maxRunCadence": 190.0, "averageTemperature": 31.0, "maxTemperature": 32.0, "minTemperature": 31.0, "averagePower": 262.0, "maxPower": 283.0, "minPower": 244.0, "normalizedPower": 262.0, "totalWork": 21.479611075842122, "groundContactTime": 247.8000030517578, "strideLength": 94.90999755859376, "verticalOscillation": 7.790000152587891, "verticalRatio": 8.210000038146973, "endLatitude": 25.03026371821761, "endLongitude": 121.45772290416062, "maxVerticalSpeed": 0.20000028610229495, "maxRespirationRate": 38.709999084472656, "avgRespirationRate": 29.260000228881836, "directWorkoutComplianceScore": 100, "avgGradeAdjustedSpeed": 2.8959999084472656, "lapIndex": 5, "lengthDTOs": [], "connectIQMeasurement": [], "intensityType": "INTERVAL", "messageIndex": 4}, {"startTimeGMT": "2024-07-17T21:07:19.0", "startLatitude": 25.03027779981494, "startLongitude": 121.4577482175082, "distance": 1000.0, "duration": 421.219, "movingDuration": 421.0, "elapsedDuration": 421.219, "elevationGain": 0.0, "elevationLoss": 1.0, "maxElevation": 6.0, "minElevation": 4.6, "averageSpeed": 2.374000072479248, "averageMovingSpeed": 2.375296912114014, "maxSpeed": 3.0510001182556157, "calories": 71.0, "bmrCalories": 9.0, "averageHR": 153.0, "maxHR": 166.0, "averageRunCadence": 181.1875, "maxRunCadence": 190.0, "averageTemperature": 32.0, "maxTemperature": 32.0, "minTemperature": 31.0, "averagePower": 217.0, "maxPower": 275.0, "minPower": 198.0, "normalizedPower": 221.0, "totalWork": 21.718273421129258, "groundContactTime": 262.0, "strideLength": 78.72000122070312, "verticalOscillation": 7.219999694824219, "verticalRatio": 9.180000305175781, "endLatitude": 25.034664468839765, "endLongitude": 121.4663044642657, "maxVerticalSpeed": 0.20000028610229495, "maxRespirationRate": 35.54999923706055, "avgRespirationRate": 27.200000762939453, "directWorkoutComplianceScore": 100, "avgGradeAdjustedSpeed": 2.38100004196167, "lapIndex": 6, "lengthDTOs": [], "connectIQMeasurement": [], "intensityType": "INTERVAL", "messageIndex": 5}, {"startTimeGMT": "2024-07-17T21:14:20.0", "startLatitude": 25.034674108028412, "startLongitude": 121.46632407791913, "distance": 1000.0, "duration": 350.133, "movingDuration": 350.0, "elapsedDuration": 350.133, "elevationGain": 1.0, "elevationLoss": 2.0, "maxElevation": 5.2, "minElevation": 3.8, "averageSpeed": 2.855999946594238, "averageMovingSpeed": 2.857142857142857, "maxSpeed": 3.115999937057495, "calories": 73.0, "bmrCalories": 8.0, "averageHR": 162.0, "maxHR": 168.0, "averageRunCadence": 184.0625, "maxRunCadence": 194.0, "averageTemperature": 31.0, "maxTemperature": 32.0, "minTemperature": 31.0, "averagePower": 256.0, "maxPower": 296.0, "minPower": 219.0, "normalizedPower": 256.0, "totalWork": 21.479611075842122, "groundContactTime": 248.5, "strideLength": 92.17999877929688, "verticalOscillation": 7.630000305175781, "verticalRatio": 8.279999732971191, "endLatitude": 25.037509286776185, "endLongitude": 121.47559982724488, "maxVerticalSpeed": 0.20000028610229495, "maxRespirationRate": 37.2599983215332, "avgRespirationRate": 29.799999237060547, "directWorkoutComplianceScore": 100, "avgGradeAdjustedSpeed": 2.8329999446868896, "lapIndex": 7, "lengthDTOs": [], "connectIQMeasurement": [], "intensityType": "INTERVAL", "messageIndex": 6}, {"startTimeGMT": "2024-07-17T21:20:10.0", "startLatitude": 25.037516495212913, "startLongitude": 121.47563151083887, "distance": 1000.0, "duration": 335.929, "movingDuration": 335.929, "elapsedDuration": 335.929, "elevationGain": 0.0, "elevationLoss": 0.0, "maxElevation": 4.6, "minElevation": 3.4, "averageSpeed": 2.9769999980926514, "averageMovingSpeed": 2.9768196341458872, "maxSpeed": 3.25600004196167, "calories": 75.0, "bmrCalories": 7.0, "averageHR": 168.0, "maxHR": 172.0, "averageRunCadence": 184.640625, "maxRunCadence": 194.0, "averageTemperature": 31.0, "maxTemperature": 31.0, "minTemperature": 31.0, "averagePower": 279.0, "maxPower": 311.0, "minPower": 257.0, "normalizedPower": 278.0, "totalWork": 22.43426045699066, "groundContactTime": 244.10000610351562, "strideLength": 97.22999877929688, "verticalOscillation": 7.800000000000001, "verticalRatio": 8.020000457763672, "endLatitude": 25.034876111894846, "endLongitude": 121.46658374927938, "maxVerticalSpeed": 0.39999985694885254, "maxRespirationRate": 42.86000061035156, "avgRespirationRate": 32.75, "directWorkoutComplianceScore": 100, "avgGradeAdjustedSpeed": 3.005000114440918, "lapIndex": 8, "lengthDTOs": [], "connectIQMeasurement": [], "intensityType": "INTERVAL", "messageIndex": 7}, {"startTimeGMT": "2024-07-17T21:25:46.0", "startLatitude": 25.0348664727062, "startLongitude": 121.46656354889274, "distance": 1000.0, "duration": 462.416, "movingDuration": 462.416, "elapsedDuration": 462.416, "elevationGain": 0.0, "elevationLoss": 0.0, "maxElevation": 4.4, "minElevation": 3.8, "averageSpeed": 2.1630001068115234, "averageMovingSpeed": 2.1625549985424795, "maxSpeed": 2.9019999504089355, "calories": 73.0, "bmrCalories": 10.0, "averageHR": 154.0, "maxHR": 169.0, "averageRunCadence": 181.765625, "maxRunCadence": 190.0, "averageTemperature": 31.0, "maxTemperature": 31.0, "minTemperature": 31.0, "averagePower": 202.0, "maxPower": 275.0, "minPower": 183.0, "normalizedPower": 207.0, "totalWork": 22.195598111703525, "groundContactTime": 266.70001220703125, "strideLength": 71.12000122070313, "verticalOscillation": 6.8500000000000005, "verticalRatio": 9.640000343322754, "endLatitude": 25.031085647642612, "endLongitude": 121.45778560079634, "maxVerticalSpeed": 0.20000028610229495, "maxRespirationRate": 37.31999969482422, "avgRespirationRate": 29.65999984741211, "directWorkoutComplianceScore": 100, "avgGradeAdjustedSpeed": 2.1619999408721924, "lapIndex": 9, "lengthDTOs": [], "connectIQMeasurement": [], "intensityType": "INTERVAL", "messageIndex": 8}, {"startTimeGMT": "2024-07-17T21:33:29.0", "startLatitude": 25.031071146950126, "startLongitude": 121.45776313729584, "distance": 1000.0, "duration": 338.97, "movingDuration": 338.97, "elapsedDuration": 338.97, "elevationGain": 2.0, "elevationLoss": 1.0, "maxElevation": 5.8, "minElevation": 3.8, "averageSpeed": 2.9500000476837154, "averageMovingSpeed": 2.9501135687488187, "maxSpeed": 3.181999921798706, "calories": 71.0, "bmrCalories": 7.0, "averageHR": 167.0, "maxHR": 171.0, "averageRunCadence": 189.40625, "maxRunCadence": 200.0, "averageTemperature": 31.0, "maxTemperature": 31.0, "minTemperature": 31.0, "averagePower": 268.0, "maxPower": 320.0, "minPower": 204.0, "normalizedPower": 267.0, "totalWork": 21.718273421129258, "groundContactTime": 242.1999969482422, "strideLength": 91.85999755859376, "verticalOscillation": 7.340000152587891, "verticalRatio": 8.010000228881836, "endLatitude": 25.025745704770088, "endLongitude": 121.45095460116863, "maxVerticalSpeed": 0.40000009536743164, "maxRespirationRate": 33.81999969482422, "avgRespirationRate": 22.81999969482422, "directWorkoutComplianceScore": 100, "avgGradeAdjustedSpeed": 2.9130001068115234, "lapIndex": 10, "lengthDTOs": [], "connectIQMeasurement": [], "intensityType": "INTERVAL", "messageIndex": 9}, {"startTimeGMT": "2024-07-17T21:39:08.0", "startLatitude": 25.025725923478603, "startLongitude": 121.45094043575227, "distance": 1000.0, "duration": 343.892, "movingDuration": 343.892, "elapsedDuration": 343.892, "elevationGain": 2.0, "elevationLoss": 2.0, "maxElevation": 7.6, "minElevation": 4.6, "averageSpeed": 2.9079999923706055, "averageMovingSpeed": 2.907889700747729, "maxSpeed": 4.479000091552734, "calories": 72.0, "bmrCalories": 8.0, "averageHR": 171.0, "maxHR": 174.0, "averageRunCadence": 185.8125, "maxRunCadence": 202.0, "averageTemperature": 31.0, "maxTemperature": 31.0, "minTemperature": 30.0, "averagePower": 266.0, "maxPower": 427.0, "minPower": 228.0, "normalizedPower": 267.0, "totalWork": 21.956935766416393, "groundContactTime": 246.1999969482422, "strideLength": 92.32999877929689, "verticalOscillation": 7.540000152587891, "verticalRatio": 8.1899995803833, "endLatitude": 25.019250819459558, "endLongitude": 121.4450120832771, "maxVerticalSpeed": 0.40000009536743164, "maxRespirationRate": 38.599998474121094, "avgRespirationRate": 20.799999237060547, "directWorkoutComplianceScore": 100, "avgGradeAdjustedSpeed": 2.8710000514984126, "lapIndex": 11, "lengthDTOs": [], "connectIQMeasurement": [], "intensityType": "INTERVAL", "messageIndex": 10}, {"startTimeGMT": "2024-07-17T21:44:52.0", "startLatitude": 25.019229697063565, "startLongitude": 121.44500001333654, "distance": 1000.0, "duration": 463.643, "movingDuration": 463.0, "elapsedDuration": 463.643, "elevationGain": 1.0, "elevationLoss": 0.0, "maxElevation": 7.2, "minElevation": 4.8, "averageSpeed": 2.1570000648498535, "averageMovingSpeed": 2.159827213822894, "maxSpeed": 2.818000078201294, "calories": 71.0, "bmrCalories": 10.0, "averageHR": 156.0, "maxHR": 173.0, "averageRunCadence": 179.90625, "maxRunCadence": 196.0, "averageTemperature": 30.0, "maxTemperature": 31.0, "minTemperature": 30.0, "averagePower": 206.0, "maxPower": 261.0, "minPower": 185.0, "normalizedPower": 208.0, "totalWork": 22.672922802277796, "groundContactTime": 268.70001220703125, "strideLength": 71.84000244140626, "verticalOscillation": 6.969999694824219, "verticalRatio": 9.720000267028809, "endLatitude": 25.01086363568902, "endLongitude": 121.4414743334055, "maxVerticalSpeed": 0.20000028610229495, "maxRespirationRate": 39.849998474121094, "avgRespirationRate": 27.809999465942383, "directWorkoutComplianceScore": 100, "avgGradeAdjustedSpeed": 2.1710000038146973, "lapIndex": 12, "lengthDTOs": [], "connectIQMeasurement": [], "intensityType": "INTERVAL", "messageIndex": 11}, {"startTimeGMT": "2024-07-17T21:52:35.0", "startLatitude": 25.01084351912141, "startLongitude": 121.44146930426359, "distance": 734.19, "duration": 303.198, "movingDuration": 302.0, "elapsedDuration": 303.198, "elevationGain": 1.0, "elevationLoss": 1.0, "maxElevation": 7.6, "minElevation": 6.4, "averageSpeed": 2.4210000038146973, "averageMovingSpeed": 2.4310927233159147, "maxSpeed": 2.818000078201294, "calories": 51.0, "bmrCalories": 7.0, "averageHR": 157.0, "maxHR": 162.0, "averageRunCadence": 182.78125, "maxRunCadence": 196.0, "averageTemperature": 30.0, "maxTemperature": 30.0, "minTemperature": 30.0, "averagePower": 222.0, "maxPower": 264.0, "minPower": 206.0, "normalizedPower": 222.0, "totalWork": 15.990377134238024, "groundContactTime": 260.70001220703125, "strideLength": 78.27000122070314, "verticalOscillation": 7.140000152587891, "verticalRatio": 9.119999885559082, "endLatitude": 25.004365732893348, "endLongitude": 121.4405757933855, "maxVerticalSpeed": 0.20000028610229495, "maxRespirationRate": 32.310001373291016, "avgRespirationRate": 27.540000915527344, "directWorkoutComplianceScore": 100, "avgGradeAdjustedSpeed": 2.388000011444092, "lapIndex": 13, "lengthDTOs": [], "connectIQMeasurement": [], "intensityType": "INTERVAL", "messageIndex": 12}], "eventDTOs": [{"startTimeGMT": "2024-07-17T20:36:15.0", "startTimeGMTDoubleValue": 1721248575000.0, "sectionTypeDTO": {"id": 4, "key": "timerTrigger", "sectionTypeKey": "TIMER_TRIGGER"}}, {"startTimeGMT": "2024-07-17T20:36:16.0", "startTimeGMTDoubleValue": 1721248576000.0, "sectionTypeDTO": {"id": 4, "key": "timerTrigger", "sectionTypeKey": "TIMER_TRIGGER"}}]}}], "max_metrics": [{"userId": 2819326, "generic": {"calendarDate": "2024-07-18", "vo2MaxPreciseValue": 53.0, "vo2MaxValue": 53.0, "fitnessAge": null, "fitnessAgeDescription": null, "maxMetCategory": 0}, "cycling": null, "heatAltitudeAcclimation": {"calendarDate": "2024-07-18", "altitudeAcclimationDate": "2024-07-18", "previousAltitudeAcclimationDate": "2024-07-18", "heatAcclimationDate": "2024-07-17", "previousHeatAcclimationDate": "2024-06-15", "altitudeAcclimation": 0, "previousAltitudeAcclimation": 0, "heatAcclimationPercentage": 100, "previousHeatAcclimationPercentage": 100, "heatTrend": "ACCLIMATIZED", "altitudeTrend": null, "currentAltitude": 13, "previousAltitude": 0, "acclimationPercentage": 0, "previousAcclimationPercentage": 0, "altitudeAcclimationLocalTimestamp": "2024-07-18T23:57:59.0"}}], "hrv_data": {"userProfilePk": 2819326, "hrvSummary": {"calendarDate": "2024-07-18", "weeklyAvg": 44, "lastNightAvg": 51, "lastNight5MinHigh": 84, "baseline": {"lowUpper": 43, "balancedLow": 46, "balancedUpper": 61, "markerValue": 0.16351318}, "status": "UNBALANCED", "feedbackPhrase": "HRV_UNBALANCED_11", "createTimeStamp": "2024-07-17T20:10:23.788"}, "hrvReadings": [], "startTimestampGMT": "2024-07-17T13:32:40.0", "endTimestampGMT": "2024-07-17T20:09:04.0", "startTimestampLocal": "2024-07-17T21:32:40.0", "endTimestampLocal": "2024-07-18T04:09:04.0", "sleepStartTimestampGMT": null, "sleepEndTimestampGMT": null, "sleepStartTimestampLocal": null, "sleepEndTimestampLocal": null}, "rhr_data": {"userProfileId": 2819326, "statisticsStartDate": "2024-07-18", "statisticsEndDate": "2024-07-18", "allMetrics": {"metricsMap": {"WELLNESS_RESTING_HEART_RATE": [{"value": 51.0, "calendarDate": "2024-07-18"}]}}, "groupedMetrics": null}, "sleep_data": {"dailySleepDTO": {"id": 1721223160000, "userProfilePK": 2819326, "calendarDate": "2024-07-18", "sleepTimeSeconds": 23789, "napTimeSeconds": 1800, "sleepWindowConfirmed": true, "sleepWindowConfirmationType": "enhanced_confirmed_final", "sleepStartTimestampGMT": 1721223160000, "sleepEndTimestampGMT": 1721247009000, "sleepStartTimestampLocal": 1721251960000, "sleepEndTimestampLocal": 1721275809000, "autoSleepStartTimestampGMT": null, "autoSleepEndTimestampGMT": null, "sleepQualityTypePK": null, "sleepResultTypePK": null, "unmeasurableSleepSeconds": 0, "deepSleepSeconds": 6720, "lightSleepSeconds": 12900, "remSleepSeconds": 4200, "awakeSleepSeconds": 60, "deviceRemCapable": true, "retro": false, "sleepFromDevice": true, "averageRespirationValue": 14.0, "lowestRespirationValue": 11.0, "highestRespirationValue": 17.0, "awakeCount": 0, "avgSleepStress": 17.0, "ageGroup": "ADULT", "sleepScoreFeedback": "POSITIVE_DEEP", "sleepScoreInsight": "POSITIVE_EXERCISE", "sleepScorePersonalizedInsight": "NOT_AVAILABLE", "sleepScores": {"totalDuration": {"qualifierKey": "FAIR", "optimalStart": 28200.0, "optimalEnd": 28200.0}, "stress": {"qualifierKey": "FAIR", "optimalStart": 0.0, "optimalEnd": 15.0}, "awakeCount": {"qualifierKey": "EXCELLENT", "optimalStart": 0.0, "optimalEnd": 1.0}, "overall": {"value": 79, "qualifierKey": "FAIR"}, "remPercentage": {"value": 18, "qualifierKey": "FAIR", "optimalStart": 21.0, "optimalEnd": 31.0, "idealStartInSeconds": 4995.69, "idealEndInSeconds": 7374.59}, "restlessness": {"qualifierKey": "EXCELLENT", "optimalStart": 0.0, "optimalEnd": 5.0}, "lightPercentage": {"value": 54, "qualifierKey": "EXCELLENT", "optimalStart": 30.0, "optimalEnd": 64.0, "idealStartInSeconds": 7136.7, "idealEndInSeconds": 15224.96}, "deepPercentage": {"value": 28, "qualifierKey": "EXCELLENT", "optimalStart": 16.0, "optimalEnd": 33.0, "idealStartInSeconds": 3806.24, "idealEndInSeconds": 7850.37}}, "sleepVersion": 2, "sleepNeed": {"userProfilePk": 2819326, "calendarDate": "2024-07-18", "deviceId": 3459189856, "timestampGmt": "2024-07-17T05:00:45", "baseline": 470, "actual": 490, "feedback": "INCREASED", "trainingFeedback": "CHRONIC", "sleepHistoryAdjustment": "NO_CHANGE", "hrvAdjustment": "INCREASING", "napAdjustment": "NO_CHANGE", "displayedForTheDay": true, "preferredActivityTracker": true}, "nextSleepNeed": {"userProfilePk": 2819326, "calendarDate": "2024-07-19", "deviceId": 3459189856, "timestampGmt": "2024-07-18T11:56:31", "baseline": 470, "actual": 470, "feedback": "NO_CHANGE_BALANCED", "trainingFeedback": "TODAYS_LOAD_AND_CHRONIC", "sleepHistoryAdjustment": "NO_CHANGE", "hrvAdjustment": "INCREASING", "napAdjustment": "DECREASING", "displayedForTheDay": true, "preferredActivityTracker": true}, "dailyNapDTOS": [{"userProfilePK": 2819326, "deviceId": 3459189856, "calendarDate": "2024-07-18", "napTimeSec": 1800, "napStartTimestampGMT": "2024-07-18T04:18:09", "napEndTimestampGMT": "2024-07-18T04:48:09", "napFeedback": "IDEAL_TIMING_IDEAL_DURATION_LOW_NEED", "napSource": 1, "napStartTimeOffset": 480, "napEndTimeOffset": 480, "createTimestampGMT": null, "updateTimestampGMT": null}]}, "sleepMovement": null, "remSleepData": true, "sleepLevels": null, "skinTempDataExists": false, "bodyBatteryChange": 59, "restingHeartRate": 51}, "training_status_data": {"userId": 2819326, "mostRecentVO2Max": {"userId": 2819326, "generic": {"calendarDate": "2024-07-18", "vo2MaxPreciseValue": 53.0, "vo2MaxValue": 53.0, "fitnessAge": null, "fitnessAgeDescription": null, "maxMetCategory": 0}, "cycling": null, "heatAltitudeAcclimation": {"calendarDate": "2024-07-18", "altitudeAcclimationDate": "2024-07-18", "previousAltitudeAcclimationDate": "2024-07-18", "heatAcclimationDate": "2024-07-17", "previousHeatAcclimationDate": "2024-06-15", "altitudeAcclimation": 0, "previousAltitudeAcclimation": 0, "heatAcclimationPercentage": 100, "previousHeatAcclimationPercentage": 100, "heatTrend": "ACCLIMATIZED", "altitudeTrend": null, "currentAltitude": 13, "previousAltitude": 0, "acclimationPercentage": 0, "previousAcclimationPercentage": 0, "altitudeAcclimationLocalTimestamp": "2024-07-18T23:57:59.0"}}, "mostRecentTrainingLoadBalance": {"userId": 2819326, "metricsTrainingLoadBalanceDTOMap": {"3459189856": {"calendarDate": "2024-07-18", "deviceId": 3459189856, "monthlyLoadAerobicLow": 1245.2357, "monthlyLoadAerobicHigh": 1149.0608, "monthlyLoadAnaerobic": 147.47017, "monthlyLoadAerobicLowTargetMin": 1055, "monthlyLoadAerobicLowTargetMax": 1599, "monthlyLoadAerobicHighTargetMin": 685, "monthlyLoadAerobicHighTargetMax": 1229, "monthlyLoadAnaerobicTargetMin": 0, "monthlyLoadAnaerobicTargetMax": 326, "trainingBalanceFeedbackPhrase": "ON_TARGET", "primaryTrainingDevice": true}}, "recordedDevices": [{"deviceId": 3459189856, "imageURL": "https://res.garmin.com/en/products/010-02809-41/v/c1_01_md.png", "deviceName": "Forerunner 965", "category": 0}]}, "mostRecentTrainingStatus": {"userId": 2819326, "latestTrainingStatusData": {"3459189856": {"calendarDate": "2024-07-18", "sinceDate": "2024-07-16", "weeklyTrainingLoad": null, "trainingStatus": 4, "timestamp": 1721253668000, "deviceId": 3459189856, "loadTunnelMin": null, "loadTunnelMax": null, "loadLevelTrend": null, "sport": "RUNNING", "subSport": "GENERIC", "fitnessTrendSport": "RUNNING", "fitnessTrend": 2, "trainingStatusFeedbackPhrase": "MAINTAINING_3", "trainingPaused": false, "acuteTrainingLoadDTO": {"acwrPercent": 52, "acwrStatus": "OPTIMAL", "acwrStatusFeedback": "FEEDBACK_2", "dailyTrainingLoadAcute": 845, "maxTrainingLoadChronic": 987.0, "minTrainingLoadChronic": 526.4, "dailyTrainingLoadChronic": 658, "dailyAcuteChronicWorkloadRatio": 1.2}, "primaryTrainingDevice": true}}, "recordedDevices": [{"deviceId": 3459189856, "imageURL": "https://res.garmin.com/en/products/010-02809-41/v/c1_01_md.png", "deviceName": "Forerunner 965", "category": 0}], "showSelector": false, "lastPrimarySyncDate": "2024-07-18"}, "heatAltitudeAcclimationDTO": null}, "training_readiness_data": [{"userProfilePK": 2819326, "calendarDate": "2024-07-18", "timestamp": "2024-07-17T20:10:10.0", "timestampLocal": "2024-07-18T04:10:10.0", "deviceId": 3459189856, "level": "MODERATE", "feedbackLong": "MOD_HRV_UNBALANCED", "feedbackShort": "LISTEN_TO_YOUR_BODY", "score": 58, "sleepScore": 79, "sleepScoreFactorPercent": 68, "sleepScoreFactorFeedback": "MODERATE", "recoveryTime": 749, "recoveryTimeFactorPercent": 80, "recoveryTimeFactorFeedback": "GOOD", "acwrFactorPercent": 92, "acwrFactorFeedback": "GOOD", "acuteLoad": 591, "stressHistoryFactorPercent": 84, "stressHistoryFactorFeedback": "GOOD", "hrvFactorPercent": 49, "hrvFactorFeedback": "MODERATE", "hrvWeeklyAverage": 44, "sleepHistoryFactorPercent": 79, "sleepHistoryFactorFeedback": "GOOD", "validSleep": true, "inputContext": null, "primaryActivityTracker": true, "recoveryTimeChangePhrase": "NO_CHANGE_SLEEP"}]}